kytos/__init__.py
kytos/cli/__init__.py
kytos/cli/commands/__init__.py
kytos/cli/commands/bug_report/__init__.py
kytos/cli/commands/bug_report/api.py
kytos/cli/commands/bug_report/parser.py
kytos/cli/commands/napps/__init__.py
kytos/cli/commands/napps/api.py
kytos/cli/commands/napps/parser.py
kytos/cli/commands/users/__init__.py
kytos/cli/commands/users/api.py
kytos/cli/commands/users/parser.py
kytos/cli/commands/web/__init__.py
kytos/cli/commands/web/api.py
kytos/cli/commands/web/parser.py
kytos/templates/skel/napp-structure/username/__init__.py
kytos/templates/skel/napp-structure/username/napp/.gitignore.template
kytos/templates/skel/napp-structure/username/napp/README.rst.template
kytos/templates/skel/napp-structure/username/napp/__init__.py.template
kytos/templates/skel/napp-structure/username/napp/kytos.json.template
kytos/templates/skel/napp-structure/username/napp/main.py.template
kytos/templates/skel/napp-structure/username/napp/openapi.yml.template
kytos/templates/skel/napp-structure/username/napp/settings.py.template
kytos/templates/skel/napp-structure/username/napp/setup.py.template
kytos/templates/skel/napp-structure/username/napp/ui/README.rst.template
kytos/utils/__init__.py
kytos/utils/client.py
kytos/utils/config.py
kytos/utils/decorators.py
kytos/utils/exceptions.py
kytos/utils/metadata.py
kytos/utils/napps.py
kytos/utils/openapi.py
kytos/utils/settings.py
kytos/utils/users.py
kytos_utils-2021.1.data/scripts/kytos
tests/unit/__init__.py
tests/unit/test_client.py
tests/unit/test_config.py
tests/unit/test_decorators.py
tests/unit/test_napps.py
tests/unit/test_openapi.py
tests/unit/test_users.py
tests/unit/commands/__init__.py
tests/unit/commands/test_napps_api.py
tests/unit/commands/test_napps_parser.py
tests/unit/commands/test_users_api.py
tests/unit/commands/test_users_parser.py
tests/unit/commands/test_web_api.py
tests/unit/commands/test_web_parser.py
kytos_utils-2021.1.dist-info/AUTHORS.rst
kytos_utils-2021.1.dist-info/LICENSE
kytos_utils-2021.1.dist-info/METADATA
kytos_utils-2021.1.dist-info/WHEEL
kytos_utils-2021.1.dist-info/top_level.txt
kytos_utils-2021.1.dist-info/RECORD
