Metadata-Version: 2.1
Name: kytos-utils
Version: 2021.1
Summary: Command line utilities to use with Kytos.
Home-page: http://github.com/kytos/kytos-utils
Author: Kytos Team
Author-email: UNKNOWN
License: MIT
Platform: UNKNOWN
Requires-Dist: certifi (==2019.11.28)
Requires-Dist: chardet (==3.0.4)
Requires-Dist: docopt (==0.6.2)
Requires-Dist: idna (==2.9)
Requires-Dist: jinja2 (==2.11.1)
Requires-Dist: markupsafe (==1.1.1)
Requires-Dist: pathspec (==0.7.0)
Requires-Dist: requests (==2.23.0)
Requires-Dist: ruamel.yaml.clib (==0.2.0)
Requires-Dist: ruamel.yaml (==0.16.10)
Requires-Dist: urllib3 (==1.25.8)
